LICENSE
MANIFEST.in
README.rst
kales.py
setup.py
kales.egg-info/PKG-INFO
kales.egg-info/SOURCES.txt
kales.egg-info/dependency_links.txt
kales.egg-info/requires.txt
kales.egg-info/top_level.txt