Metadata-Version: 1.0
Name: kales
Version: 0.1.1
Summary: Python client to the OpenCalais API
Home-page: http://github.com/cyberdelia/kales
Author: Timothée Peignier
Author-email: timothee.peignier@tryphon.org
License: Copyright (c) 2012, Timothée Peignier
